python_yeet/__init__.py
python_yeet/app.py
python_yeet/controllers.py
python_yeet/db.py
python_yeet/handlers.py
python_yeet/helpers.py
python_yeet/orm.py
python_yeet/templates/404.html
python_yeet-1.0.2.dist-info/LICENSE
python_yeet-1.0.2.dist-info/METADATA
python_yeet-1.0.2.dist-info/WHEEL
python_yeet-1.0.2.dist-info/RECORD
