Metadata-Version: 2.1
Name: python-yeet
Version: 1.0.2
Summary: yeet is a simple Python framework
Author: Yakser
Author-email: iaksanov2044@mail.ru
Requires-Python: >=3.9,<4.0
Classifier: Programming Language :: Python :: 3
Classifier: Programming Language :: Python :: 3.9
Classifier: Programming Language :: Python :: 3.10
Classifier: Programming Language :: Python :: 3.11
Requires-Dist: cryptography (>=39.0.2,<40.0.0)
Requires-Dist: jinja2 (>=3.1.2,<4.0.0)
Requires-Dist: pymysql (>=1.0.2,<2.0.0)
